llama_index/packs/rag_evaluator/__init__.py
llama_index/packs/rag_evaluator/base.py
llama_index_packs_rag_evaluator-0.4.1.dist-info/METADATA
llama_index_packs_rag_evaluator-0.4.1.dist-info/WHEEL
llama_index_packs_rag_evaluator-0.4.1.dist-info/licenses/LICENSE
llama_index_packs_rag_evaluator-0.4.1.dist-info/RECORD
