Metadata-Version: 2.4
Name: llama-index-packs-rag-evaluator
Version: 0.4.1
Summary: llama-index packs rag_evaluator integration
Author-email: Your Name <you@example.com>
Maintainer: nerdai
License-Expression: MIT
License-File: LICENSE
Keywords: benchmarks,evaluation,rag
Requires-Python: <4.0,>=3.9
Requires-Dist: llama-index-embeddings-openai<0.6,>=0.5.0
Requires-Dist: llama-index-llms-openai<0.6,>=0.5.0
Requires-Dist: pandas
